scrapy_aiohttp/__init__.py
scrapy_aiohttp/middleware.py
scrapy_aiohttp/request.py
scrapy_aiohttp/server.py
scrapy_aiohttp/utils/__init__.py
scrapy_aiohttp/utils/constants.py
scrapy_aiohttp/utils/exceptions.py
scrapy_aiohttp/utils/simple_spider.py
scrapy_aiohttp/utils/types.py
scrapy_aiohttp-0.1.2.dist-info/LICENSE
scrapy_aiohttp-0.1.2.dist-info/METADATA
scrapy_aiohttp-0.1.2.dist-info/WHEEL
scrapy_aiohttp-0.1.2.dist-info/RECORD
