Metadata-Version: 2.1
Name: scrapy_aiohttp
Version: 0.1.2
Summary: Scrapy middleware for sending requests with aiohttp.
License: BSD-3-Clause
Author: Artem Serdechnyi
Author-email: serdechnyi.art@gmail.com
Requires-Python: >=3.10,<4.0
Classifier: Development Status :: 3 - Alpha
Classifier: Framework :: Scrapy
Classifier: Intended Audience :: Developers
Classifier: License :: OSI Approved :: BSD License
Classifier: Programming Language :: Python
Classifier: Programming Language :: Python :: 3
Classifier: Programming Language :: Python :: 3.10
Classifier: Programming Language :: Python :: 3.11
Classifier: Programming Language :: Python :: 3.12
Classifier: Topic :: Internet :: WWW/HTTP
Classifier: Topic :: Software Development :: Libraries :: Application Frameworks
Classifier: Topic :: Software Development :: Libraries :: Python Modules
Requires-Dist: aiohttp (>=3.8.6,<4.0.0)
Requires-Dist: coverage[toml] (>=7.3.2,<8.0.0)
Requires-Dist: scrapy (>=2.11.0,<3.0.0)
